python_outbox/__init__.py
python_outbox/base/__init__.py
python_outbox/base/mapper.py
python_outbox/base/producer.py
python_outbox/base/publisher.py
python_outbox/base/runner.py
python_outbox/base/source.py
python_outbox/base/storage_box.py
python_outbox/base/type.py
python_outbox/generic/__init__.py
python_outbox/generic/mapper.py
python_outbox/generic/producer.py
python_outbox/generic/publisher.py
python_outbox/generic/runner.py
python_outbox/sqlalchemy_outbox/__init__.py
python_outbox/sqlalchemy_outbox/sqlalchemy_base.py
python_outbox/sqlalchemy_outbox/sqlalchemy_mapper.py
python_outbox/sqlalchemy_outbox/sqlalchemy_producer.py
python_outbox/sqlalchemy_outbox/sqlalchemy_source.py
python_outbox/sqlalchemy_outbox/sqlalchemy_storage_box.py
python_outbox-0.1.8.dist-info/WHEEL
python_outbox-0.1.8.dist-info/METADATA
python_outbox-0.1.8.dist-info/RECORD
